haibedz/__init__.py
haibedz-0.2.0.dist-info/LICENSE
haibedz-0.2.0.dist-info/METADATA
haibedz-0.2.0.dist-info/WHEEL
haibedz-0.2.0.dist-info/top_level.txt
haibedz-0.2.0.dist-info/RECORD
