Metadata-Version: 2.1
Name: haibedz
Version: 0.2.0
Summary: Module Added To The Code Generated By Haibedz
Author-email: Hai Be Chuche <haibe@gmail.com>
Project-URL: Homepage, https://github.com/billythegoat356/
Project-URL: Bug Tracker, https://github.com/billythegoat356/
Classifier: Programming Language :: Python :: 3
Classifier: License :: OSI Approved :: MIT License
Classifier: Operating System :: OS Independent
Requires-Python: >=3.8
License-File: LICENSE
